MANIFEST.in
VERSION
setup.py
canonical.ext.repository.egg-info/PKG-INFO
canonical.ext.repository.egg-info/SOURCES.txt
canonical.ext.repository.egg-info/dependency_links.txt
canonical.ext.repository.egg-info/requires.txt
canonical.ext.repository.egg-info/top_level.txt
canonical/ext/repository/__init__.py
canonical/ext/repository/_basemodelrepository.py
canonical/ext/repository/package.json
canonical/ext/repository/protocols/__init__.py
canonical/ext/repository/protocols/_imodelrepository.py